tembo/__init__.py
tembo/__main__.py
tembo/_version.py
tembo/cli/__init__.py
tembo/cli/cli.py
tembo/exceptions.py
tembo/journal/__init__.py
tembo/journal/pages.py
tembo/utils/__init__.py
tembo-0.0.8.dist-info/entry_points.txt
tembo-0.0.8.dist-info/LICENSE.md
tembo-0.0.8.dist-info/WHEEL
tembo-0.0.8.dist-info/METADATA
tembo-0.0.8.dist-info/RECORD
